purgo_ingest/__init__.py
purgo_ingest/cli.py
purgo_ingest/cloning.py
purgo_ingest/config.py
purgo_ingest/entrypoint.py
purgo_ingest/ingestion.py
purgo_ingest/output_formatters.py
purgo_ingest/query_parsing.py
purgo_ingest/schemas/__init__.py
purgo_ingest/schemas/filesystem_schema.py
purgo_ingest/schemas/ingestion_schema.py
purgo_ingest/utils/__init__.py
purgo_ingest/utils/exceptions.py
purgo_ingest/utils/file_utils.py
purgo_ingest/utils/git_utils.py
purgo_ingest/utils/ignore_patterns.py
purgo_ingest/utils/ingestion_utils.py
purgo_ingest/utils/notebook_utils.py
purgo_ingest/utils/path_utils.py
purgo_ingest/utils/query_parser_utils.py
purgo_ingest/utils/timeout_wrapper.py
purgo_ingest/utils/windows_helper.py
server/__init__.py
server/main.py
server/query_processor.py
server/server_config.py
server/server_utils.py
server/routers/__init__.py
server/routers/download.py
server/routers/dynamic.py
server/routers/index.py
purgo_ingest-0.1.4.dist-info/LICENSE
purgo_ingest-0.1.4.dist-info/METADATA
purgo_ingest-0.1.4.dist-info/WHEEL
purgo_ingest-0.1.4.dist-info/entry_points.txt
purgo_ingest-0.1.4.dist-info/top_level.txt
purgo_ingest-0.1.4.dist-info/RECORD
