Metadata-Version: 2.1
Name: purgo_ingest
Version: 0.1.4
Summary: CLI tool to analyze and create text dumps of codebases for LLMs
Author-email: Your Name <your.email@example.com>
License: MIT
Project-URL: homepage, https://github.com/yourusername/purgo_ingest
Project-URL: repository, https://github.com/yourusername/purgo_ingest
Project-URL: documentation, https://github.com/yourusername/purgo_ingest#readme
Classifier: Development Status :: 3 - Alpha
Classifier: Intended Audience :: Developers
Classifier: Programming Language :: Python :: 3.8
Classifier: Programming Language :: Python :: 3.9
Classifier: Programming Language :: Python :: 3.10
Classifier: Programming Language :: Python :: 3.11
Classifier: Programming Language :: Python :: 3.12
Classifier: Programming Language :: Python :: 3.13
Requires-Python: >=3.8
License-File: LICENSE
Requires-Dist: click>=8.0.0
Requires-Dist: fastapi[standard]>=0.109.1
Requires-Dist: pydantic
Requires-Dist: python-dotenv
Requires-Dist: slowapi
Requires-Dist: starlette>=0.40.0
Requires-Dist: tiktoken
Requires-Dist: tomli
Requires-Dist: uvicorn>=0.11.7
Requires-Dist: typing-extensions; python_version < "3.10"
